main.py
officemath2latex.py
officemath2latex-0.1.0.dist-info/METADATA
officemath2latex-0.1.0.dist-info/WHEEL
officemath2latex-0.1.0.dist-info/entry_points.txt
officemath2latex-0.1.0.dist-info/top_level.txt
officemath2latex-0.1.0.dist-info/RECORD
