Metadata-Version: 2.4
Name: officemath2latex
Version: 0.1.0
Summary: OfficeMath (OMML) to LaTeX converter
Requires-Python: >=3.10
Requires-Dist: lxml>=4.9
